tellmewhattodo/__init__.py
tellmewhattodo/app/__init__.py
tellmewhattodo/app/app.py
tellmewhattodo/cli.py
tellmewhattodo/job/__init__.py
tellmewhattodo/job/extractor.py
tellmewhattodo/job/job.py
tellmewhattodo/job/storage.py
tellmewhattodo/models/alert.py
tellmewhattodo/settings.py
tellmewhattodo-2.1.1.dist-info/entry_points.txt
tellmewhattodo-2.1.1.dist-info/WHEEL
tellmewhattodo-2.1.1.dist-info/METADATA
tellmewhattodo-2.1.1.dist-info/RECORD
